<?xml version="1.0" encoding="utf-8"?>
<Patch>

	<!-- ====== Floater ====== -->

	<Operation Class="PatchOperationConditional">
		<xpath>Defs/BodyDef[defName="IM_MechanicalFloater"]/corePart/groups</xpath>
		<nomatch Class="PatchOperationAdd">
			<xpath>Defs/BodyDef[defName="IM_MechanicalFloater"]/corePart</xpath>
			<value>
				<groups>
					<li>CoveredByNaturalArmor</li>
				</groups>
			</value>
		</nomatch>
		<match Class="PatchOperationAdd">
			<xpath>Defs/BodyDef[defName="IM_MechanicalFloater"]/corePart/groups</xpath>
			<value>
				<li>CoveredByNaturalArmor</li>
			</value>
		</match>
	</Operation>

	<Operation Class="PatchOperationConditional">
		<xpath>Defs/BodyDef[defName="IM_MechanicalFloater"]/corePart/parts/li[def="IM_JetIntake"]/groups</xpath>
		<nomatch Class="PatchOperationAdd">
			<xpath>Defs/BodyDef[defName="IM_MechanicalFloater"]/corePart/parts/li[def="IM_JetIntake"]</xpath>
			<value>
				<groups>
					<li>CoveredByNaturalArmor</li>
				</groups>
			</value>
		</nomatch>
		<match Class="PatchOperationAdd">
			<xpath>Defs/BodyDef[defName="IM_MechanicalFloater"]/corePart/parts/li[def="IM_JetIntake"]/groups</xpath>
			<value>
				<li>CoveredByNaturalArmor</li>
			</value>
		</match>
	</Operation>

	<Operation Class="PatchOperationConditional">
		<xpath>Defs/BodyDef[defName="IM_MechanicalFloater"]/corePart/parts/li[def="MechanicalNeck"]/groups</xpath>
		<nomatch Class="PatchOperationAdd">
			<xpath>Defs/BodyDef[defName="IM_MechanicalFloater"]/corePart/parts/li[def="MechanicalNeck"]</xpath>
			<value>
				<groups>
					<li>CoveredByNaturalArmor</li>
				</groups>
			</value>
		</nomatch>
		<match Class="PatchOperationAdd">
			<xpath>Defs/BodyDef[defName="IM_MechanicalFloater"]/corePart/parts/li[def="MechanicalNeck"]/groups</xpath>
			<value>
				<li>CoveredByNaturalArmor</li>
			</value>
		</match>
	</Operation>

	<Operation Class="PatchOperationConditional">
		<xpath>Defs/BodyDef[defName="IM_MechanicalFloater"]/corePart/parts/li[def="MechanicalNeck"]/parts/li[def="MechanicalHead"]/groups</xpath>
		<nomatch Class="PatchOperationAdd">
			<xpath>Defs/BodyDef[defName="IM_MechanicalFloater"]/corePart/parts/li[def="MechanicalNeck"]/parts/li[def="MechanicalHead"]</xpath>
			<value>
				<groups>
					<li>CoveredByNaturalArmor</li>
				</groups>
			</value>
		</nomatch>
		<match Class="PatchOperationAdd">
			<xpath>Defs/BodyDef[defName="IM_MechanicalFloater"]/corePart/parts/li[def="MechanicalNeck"]/parts/li[def="MechanicalHead"]/groups</xpath>
			<value>
				<li>CoveredByNaturalArmor</li>
			</value>
		</match>
	</Operation>

	<Operation Class="PatchOperationConditional">
		<xpath>Defs/BodyDef[defName="IM_MechanicalFloater"]/corePart/parts/li[def="MechanicalNeck"]/parts/li[def="MechanicalHead"]/parts/li[def="SightSensor"]/groups</xpath>
		<nomatch Class="PatchOperationAdd">
			<xpath>Defs/BodyDef[defName="IM_MechanicalFloater"]/corePart/parts/li[def="MechanicalNeck"]/parts/li[def="MechanicalHead"]/parts/li[def="SightSensor"]</xpath>
			<value>
				<groups>
					<li>CoveredByNaturalArmor</li>
				</groups>
			</value>
		</nomatch>
		<match Class="PatchOperationAdd">
			<xpath>Defs/BodyDef[defName="IM_MechanicalFloater"]/corePart/parts/li[def="MechanicalNeck"]/parts/li[def="MechanicalHead"]/parts/li[def="SightSensor"]/groups</xpath>
			<value>
				<li>CoveredByNaturalArmor</li>
			</value>
		</match>
	</Operation>

	<Operation Class="PatchOperationConditional">
		<xpath>Defs/BodyDef[defName="IM_MechanicalFloater"]/corePart/parts/li[def="MechanicalNeck"]/parts/li[def="MechanicalHead"]/parts/li[def="HearingSensor"]/groups</xpath>
		<nomatch Class="PatchOperationAdd">
			<xpath>Defs/BodyDef[defName="IM_MechanicalFloater"]/corePart/parts/li[def="MechanicalNeck"]/parts/li[def="MechanicalHead"]/parts/li[def="HearingSensor"]</xpath>
			<value>
				<groups>
					<li>CoveredByNaturalArmor</li>
				</groups>
			</value>
		</nomatch>
		<match Class="PatchOperationAdd">
			<xpath>Defs/BodyDef[defName="IM_MechanicalFloater"]/corePart/parts/li[def="MechanicalNeck"]/parts/li[def="MechanicalHead"]/parts/li[def="HearingSensor"]/groups</xpath>
			<value>
				<li>CoveredByNaturalArmor</li>
			</value>
		</match>
	</Operation>

	<Operation Class="PatchOperationConditional">
		<xpath>Defs/BodyDef[defName="IM_MechanicalFloater"]/corePart/parts/li[def="MechanicalNeck"]/parts/li[def="MechanicalHead"]/parts/li[def="SmellSensor"]/groups</xpath>
		<nomatch Class="PatchOperationAdd">
			<xpath>Defs/BodyDef[defName="IM_MechanicalFloater"]/corePart/parts/li[def="MechanicalNeck"]/parts/li[def="MechanicalHead"]/parts/li[def="SmellSensor"]</xpath>
			<value>
				<groups>
					<li>CoveredByNaturalArmor</li>
				</groups>
			</value>
		</nomatch>
		<match Class="PatchOperationAdd">
			<xpath>Defs/BodyDef[defName="IM_MechanicalFloater"]/corePart/parts/li[def="MechanicalNeck"]/parts/li[def="MechanicalHead"]/parts/li[def="SmellSensor"]/groups</xpath>
			<value>
				<li>CoveredByNaturalArmor</li>
			</value>
		</match>
	</Operation>

	<Operation Class="PatchOperationConditional">
		<xpath>Defs/BodyDef[defName="IM_MechanicalFloater"]/corePart/parts/li[def="MechanicalShoulder"]/groups</xpath>
		<nomatch Class="PatchOperationAdd">
			<xpath>Defs/BodyDef[defName="IM_MechanicalFloater"]/corePart/parts/li[def="MechanicalShoulder"]</xpath>
			<value>
				<groups>
					<li>CoveredByNaturalArmor</li>
				</groups>
			</value>
		</nomatch>
		<match Class="PatchOperationAdd">
			<xpath>Defs/BodyDef[defName="IM_MechanicalFloater"]/corePart/parts/li[def="MechanicalShoulder"]/groups</xpath>
			<value>
				<li>CoveredByNaturalArmor</li>
			</value>
		</match>
	</Operation>

	<Operation Class="PatchOperationConditional">
		<xpath>Defs/BodyDef[defName="IM_MechanicalFloater"]/corePart/parts/li[def="MechanicalShoulder"]/parts/li[def="MechanicalArm"]/groups</xpath>
		<nomatch Class="PatchOperationAdd">
			<xpath>Defs/BodyDef[defName="IM_MechanicalFloater"]/corePart/parts/li[def="MechanicalShoulder"]/parts/li[def="MechanicalArm"]</xpath>
			<value>
				<groups>
					<li>CoveredByNaturalArmor</li>
				</groups>
			</value>
		</nomatch>
		<match Class="PatchOperationAdd">
			<xpath>Defs/BodyDef[defName="IM_MechanicalFloater"]/corePart/parts/li[def="MechanicalShoulder"]/parts/li[def="MechanicalArm"]/groups</xpath>
			<value>
				<li>CoveredByNaturalArmor</li>
			</value>
		</match>
	</Operation>

	<Operation Class="PatchOperationConditional">
		<xpath>Defs/BodyDef[defName="IM_MechanicalFloater"]/corePart/parts/li[def="MechanicalShoulder"]/parts/li[def="MechanicalArm"]/parts/li[def="MechanicalHand"]/groups</xpath>
		<nomatch Class="PatchOperationAdd">
			<xpath>Defs/BodyDef[defName="IM_MechanicalFloater"]/corePart/parts/li[def="MechanicalShoulder"]/parts/li[def="MechanicalArm"]/parts/li[def="MechanicalHand"]</xpath>
			<value>
				<groups>
					<li>CoveredByNaturalArmor</li>
				</groups>
			</value>
		</nomatch>
		<match Class="PatchOperationAdd">
			<xpath>Defs/BodyDef[defName="IM_MechanicalFloater"]/corePart/parts/li[def="MechanicalShoulder"]/parts/li[def="MechanicalArm"]/parts/li[def="MechanicalHand"]/groups</xpath>
			<value>
				<li>CoveredByNaturalArmor</li>
			</value>
		</match>
	</Operation>

	<Operation Class="PatchOperationConditional">
		<xpath>Defs/BodyDef[defName="IM_MechanicalFloater"]/corePart/parts/li[def="MechanicalShoulder"]/parts/li[def="MechanicalArm"]/parts/li[def="MechanicalHand"]/parts/li[def="MechanicalFinger"]/groups</xpath>
		<nomatch Class="PatchOperationAdd">
			<xpath>Defs/BodyDef[defName="IM_MechanicalFloater"]/corePart/parts/li[def="MechanicalShoulder"]/parts/li[def="MechanicalArm"]/parts/li[def="MechanicalHand"]/parts/li[def="MechanicalFinger"]</xpath>
			<value>
				<groups>
					<li>CoveredByNaturalArmor</li>
				</groups>
			</value>
		</nomatch>
		<match Class="PatchOperationAdd">
			<xpath>Defs/BodyDef[defName="IM_MechanicalFloater"]/corePart/parts/li[def="MechanicalShoulder"]/parts/li[def="MechanicalArm"]/parts/li[def="MechanicalHand"]/parts/li[def="MechanicalFinger"]/groups</xpath>
			<value>
				<li>CoveredByNaturalArmor</li>
			</value>
		</match>
	</Operation>

</Patch>